{
  "date": "2026-05-22",
  "twitter": {
    "date": "2026-05-22",
    "handle": "DrJackKruse",
    "tweet_count": 14,
    "tweets": [
      {
        "id": "2057660191395475575",
        "text": "Search my mithack #722 on Melatonin.",
        "time_utc": "03:09",
        "type": "quote",
        "likes": 20,
        "views": 3388,
        "quoted": {
          "user": "LightOverPrism",
          "text": "@stephanieseneff Thank you for your important work. \n\nRecently you were quoted saying \"I don't take any supplements. None of these organic molecules. None.”\n\nWhat should we do in the case of Melatonin? Avoid it?  @DrJackKruse \nOr take it + get morning sun to improve sleep and more?"
        }
      },
      {
        "id": "2057651116972646824",
        "text": "Teeth are not passive chewing stones; they are highly specialized, solid-state crystalline light-pipes and mineral-dielectric capacitors derived directly from the embryonic ectoderm; the identical cellular lineage that wraps and forms the brain, the neural crest, and the retina.",
        "time_utc": "02:33",
        "type": "post",
        "likes": 100,
        "views": 4283,
        "media": [
          "photo"
        ]
      },
      {
        "id": "2057648334878175340",
        "text": "IYKYK",
        "time_utc": "02:22",
        "type": "quote",
        "likes": 24,
        "views": 4546,
        "quoted": {
          "user": "toobaffled",
          "text": "We can’t continue to keep ignoring these tragedies. Only someone who has something to hide would not want to get to the bottom of these sudden deaths and Turbo Cancers.\n\nUS DOCTOR DIES SUDDENLY weeks after her 15 year old daughter dies of Cancer: \n\n41 year old New York Breast"
        }
      },
      {
        "id": "2057648009895153897",
        "text": "RT @AmmousMD: Most medications are given to treat side effects of other medications.",
        "time_utc": "02:21",
        "type": "retweet",
        "quoted": {
          "user": "AmmousMD",
          "text": "Most medications are given to treat side effects of other medications."
        }
      },
      {
        "id": "2057644835939488029",
        "text": "RT @MartyBent: You absolutely love to see it.",
        "time_utc": "02:08",
        "type": "retweet",
        "quoted": {
          "user": "MartyBent",
          "text": "You absolutely love to see it."
        }
      },
      {
        "id": "2057643892581790054",
        "text": "RT @Kevin_McKernan: @AlexBerenson Alex,\n\nBreath..\n\nYou’re not following any evidence.\nYou’re posting studies you don’t read for clicks.\n\nI’…",
        "time_utc": "02:05",
        "type": "retweet",
        "views": 2,
        "quoted": {
          "user": "Kevin_McKernan",
          "text": "@AlexBerenson Alex,\n\nBreath..\n\nYou’re not following any evidence.\nYou’re posting studies you don’t read for clicks.\n\nI’ve engaged with the data and have offered multiples times to debate you with @Ravarora1 and you run away every time.\n\nWhy not engage now?\n\nIf you’re so dedicated to"
        }
      },
      {
        "id": "2057642189216158059",
        "text": "RT @AmmousMD: Women have been giving birth forever. Literally.\n\nDon’t let your doctor turn pregnancy into a disease.\n\nThe less testing, the…",
        "time_utc": "01:58",
        "type": "retweet",
        "views": 3,
        "quoted": {
          "user": "AmmousMD",
          "text": "Women have been giving birth forever. Literally.\n\nDon’t let your doctor turn pregnancy into a disease.\n\nThe less testing, the better."
        }
      },
      {
        "id": "2057638832028197305",
        "text": "RT @AmmousMD: Blue light and EMF.",
        "time_utc": "01:45",
        "type": "retweet",
        "views": 2,
        "quoted": {
          "user": "AmmousMD",
          "text": "Blue light and EMF."
        }
      },
      {
        "id": "2057638312173617423",
        "text": "Compliance cost is steep",
        "time_utc": "01:42",
        "type": "quote",
        "likes": 49,
        "views": 4217,
        "quoted": {
          "user": "toobaffled",
          "text": "California.  38 years old.  Professor at Clovis Community College dies from a heart attack.  Board covering Clovis mandated covid shots:  Clovis Community College District's Board of Trustees approved a vaccine mandate for students, employees, contractors, and visitors in August"
        }
      },
      {
        "id": "2057636625362923680",
        "text": "I see at least 5 things wrong here.",
        "time_utc": "01:36",
        "type": "quote",
        "likes": 32,
        "views": 13156,
        "quoted": {
          "user": "toobaffled",
          "text": "Poland.  41 years old.  Bodybuilder, personal trainer, and model, died suddenly and unexpectedly.  His agent said he had no idea he was in ill health and looked great prior to his death.  \n\n'His agent Ewa Rączy said: “We’d only seen each other recently through work. He was"
        }
      },
      {
        "id": "2057630638396649929",
        "text": "Expect more of that.",
        "time_utc": "01:12",
        "type": "quote",
        "likes": 15,
        "views": 3728,
        "quoted": {
          "user": "Promptmethus",
          "text": "@DrJackKruse I'm not sure what the linked post is claiming, but I can report it up here from just below the Northwest Territory border in Alberta that the weather is absolutely bonkers for this season and we are nearing the end of the month. And we still have the same temperatures that we've"
        }
      },
      {
        "id": "2057621031708164144",
        "text": "This tweet is so retarded it is not funny because its dangerous.  It is fueled by guys like Thomas Seyfried.  \n\nThe assertion that cancer cells cannot process fats is flatly disproven by the physics of tumor adaptation. When a patient cuts 100% of their glucose to force a state https://t.co/96NDGXVsMM",
        "time_utc": "00:34",
        "type": "quote",
        "likes": 72,
        "views": 6612,
        "quoted": {
          "user": "gemoscatelli",
          "text": "If you or one of your family members have been diagnosed with cancer and the oncologist recommends to continue with a \"Mediterranean diet\" consisting in 3 meals per day full of glucose ask the following question:  \nWhy is radioactive glucose (18F-FDG) used as contrast in Positron"
        },
        "media": [
          "photo"
        ]
      },
      {
        "id": "2057614115086929973",
        "text": "Given the Telluric currents and the state of Kansas magnetic field and the recent changes to the Schumann resonance,   Makes decentralized sense.",
        "time_utc": "00:06",
        "type": "quote",
        "likes": 32,
        "views": 3489,
        "quoted": {
          "user": "cynthia_hert",
          "text": "People across the Midwest reported A RARE “FALLING HOLE”.\nAs sunrise painted the skies above Kansas, Nebraska, Iowa, and parts of the Dakotas, stunned residents watched clouds suddenly open into a massive glowing circle — creating what looked like a giant gateway.\nMay 19, 2026"
        }
      },
      {
        "id": "2057614000922165638",
        "text": "good.",
        "time_utc": "00:06",
        "type": "quote",
        "likes": 7,
        "views": 2711,
        "quoted": {
          "user": "Tom_Idaho",
          "text": "@DrJackKruse I don't think @SunWeatherMan agrees"
        }
      }
    ]
  },
  "forum": {
    "post_count": 12,
    "window_hours": 24,
    "posts": [
      {
        "thread_title": "THE GREAT MAGNETIC SHORT.....WHAT TO EXPECT IN FACTOR Y",
        "thread_url": "https://forum.jackkruse.com/threads/the-great-magnetic-short-what-to-expect-in-factor-y.32503/unread",
        "author": "Jenelle",
        "posted_at": "2026-05-22T10:34:30.000Z",
        "forum_name": "Jack Kruse",
        "content": null
      },
      {
        "thread_title": "ALL THINGS DIABETES",
        "thread_url": "https://forum.jackkruse.com/threads/all-things-diabetes.32550/unread",
        "author": "dnborge",
        "posted_at": "2026-05-22T08:29:27.000Z",
        "forum_name": "Jack Kruse",
        "content": "This is breath taking analysis. Seriously... wow. All of a sudden, such context has been applied to any number of things within our machinery that it all makes so much sense. Thanks again Dr Jack."
      },
      {
        "thread_title": "When you begin with a Silver Gold or Platinum membership",
        "thread_url": "https://forum.jackkruse.com/threads/when-you-begin-with-a-silver-gold-or-platinum-membership.19027/unread",
        "author": "Beccy",
        "posted_at": "2026-05-22T06:00:14.000Z",
        "forum_name": "Jack Kruse",
        "content": "I have been doing sunrises since August and having uvex blue blocking glasses and covering my skin at knight."
      },
      {
        "thread_title": "David's Journal - Finally Aligned",
        "thread_url": "https://forum.jackkruse.com/threads/davids-journal-finally-aligned.12031/unread",
        "author": "DavidL",
        "posted_at": "2026-05-22T04:09:16.000Z",
        "forum_name": "DavidL",
        "content": "When I was seven years old, my father took me to Head Smashed In Buffalo Jump and said, \"You know what happens to animals and people that run with the herd, that do things out of fear? They are lead over a cliff to their death. Don't follow the crowd David, think for yourself. If you find yourself in the majority be worried.\""
      },
      {
        "thread_title": "Modeling Through Time: Johan's Notes on Life",
        "thread_url": "https://forum.jackkruse.com/threads/modeling-through-time-johans-notes-on-life.22865/unread",
        "author": "Quintavious the 3rd",
        "posted_at": "2026-05-22T01:16:35.000Z",
        "forum_name": "Johan Lindøm",
        "content": "Courage is forward movement while embracing fear. Thinking for yourself is courage. What's rare is the courage to follow it to the dark places where it leads. One person with courage is the only majority you need to succeed in life. Matter organizes itself according to how you think!!"
      },
      {
        "thread_title": "I Stay Away...From nnEMF",
        "thread_url": "https://forum.jackkruse.com/threads/i-stay-away-from-nnemf.30545/unread",
        "author": "DLO",
        "posted_at": "2026-05-22T01:12:36.000Z",
        "forum_name": "Mr.AJ",
        "content": "Walk around the outside and see where it is coming from. Normally one side is the strongest, then look for towers. If no towers on that side close by good chance it is the neighbors WiFi. In single story buildings shielding the fence with wire mesh (metal window screen) can be a quick easy fix."
      },
      {
        "thread_title": "Anthony Smith EMF posts/photos for family & friends",
        "thread_url": "https://forum.jackkruse.com/threads/anthony-smith-emf-posts-photos-for-family-friends.28747/unread",
        "author": "bulkbiceps",
        "posted_at": "2026-05-21T21:49:30.000Z",
        "forum_name": "Anthony Smith",
        "content": null
      },
      {
        "thread_title": "Rusty's EMF Thread",
        "thread_url": "https://forum.jackkruse.com/threads/rustys-emf-thread.32381/unread",
        "author": "Rusty",
        "posted_at": "2026-05-21T21:19:25.000Z",
        "forum_name": "Rusty",
        "content": "Full stack UX Designer, Frontend Developer, Independent Health Researcher, Bitcoin Maximalist. Living at 15N in India. Follow me on X : @ze_rusty Follow me on Nostr : njump.me/npub16guycjkxy04e79dwfjejaeafkqlqyq5q94f0yw2l9m50vse32x4qsyulsy Get my book → 100+ Simple EMF hacks Get my app → TAP ZAP for MacOS & Windows"
      },
      {
        "thread_title": "Jacks Optimal Journal",
        "thread_url": "https://forum.jackkruse.com/threads/jacks-optimal-journal.25708/unread",
        "author": "AlbertW",
        "posted_at": "2026-05-21T21:05:15.000Z",
        "forum_name": "Jacks",
        "content": "Miriam Richard 214-325-2243 tico.miriam@gmail.com Gut Feeling ; Gut Healing https://www.facebook.com/gutfeelingguthealing Dogs in Vests www.dogsinvests.com"
      },
      {
        "thread_title": "Hair color change",
        "thread_url": "https://forum.jackkruse.com/threads/hair-color-change.30362/unread",
        "author": "chiropierce",
        "posted_at": "2026-05-21T20:37:17.000Z",
        "forum_name": "Jingpaw",
        "content": null
      },
      {
        "thread_title": "(Potential) Gene Therapy for Primary Immunodeficiency Disorder?",
        "thread_url": "https://forum.jackkruse.com/threads/potential-gene-therapy-for-primary-immunodeficiency-disorder.30343/unread",
        "author": "FDDio",
        "posted_at": "2026-05-21T19:19:22.000Z",
        "forum_name": "FDDio",
        "content": null
      },
      {
        "thread_title": "9 yr old - redox, melanin and Mito rx journal",
        "thread_url": "https://forum.jackkruse.com/threads/9-yr-old-redox-melanin-and-mito-rx-journal.28920/unread",
        "author": "Niki Stanton",
        "posted_at": "2026-05-21T18:38:40.000Z",
        "forum_name": "Niki Stanton",
        "content": "Age: 60 Sex: M Joined JackKruse.com: Dec 2024 Location: Toronto, ON Current Passion: Seeking effective treatments and therapies for my daughter, who has an extremely rare Primary Immunodeficiency Disorder (PID),"
      }
    ]
  }
}